{
  "scoring": {
    "Second": 1,
    "Sweet 16": 2,
    "Elite 8": 3,
    "Final 4": 4,
    "Finalists": 5,
    "Champions": 6
  },
  "standings": [
    {
      "name": "Megan",
      "score": 20
    },
    {
      "name": "Mom",
      "score": 18
    },
    {
      "name": "Jared",
      "score": 18
    },
    {
      "name": "Gavin",
      "score": 17
    },
    {
      "name": "Dad",
      "score": 16
    },
    {
      "name": "Lauren",
      "score": 16
    },
    {
      "name": "Molly",
      "score": 15
    }
  ],
  "master": {
    "regions": [
      {
        "matchups": [
          [
            {
              "seed": 1,
              "name": "Duke",
              "row": 2
            },
            {
              "seed": 16,
              "name": "Siena",
              "row": 4
            }
          ],
          [
            {
              "seed": 8,
              "name": "Ohio State",
              "row": 6
            },
            {
              "seed": 9,
              "name": "TCU",
              "row": 8
            }
          ],
          [
            {
              "seed": 5,
              "name": "St. John's",
              "row": 10
            },
            {
              "seed": 12,
              "name": "Northern Iowa",
              "row": 12
            }
          ],
          [
            {
              "seed": 4,
              "name": "Kansas",
              "row": 14
            },
            {
              "seed": 13,
              "name": "Cal Baptist",
              "row": 16
            }
          ],
          [
            {
              "seed": 6,
              "name": "Louisville",
              "row": 18
            },
            {
              "seed": 11,
              "name": "South Florida",
              "row": 20
            }
          ],
          [
            {
              "seed": 3,
              "name": "Michigan State",
              "row": 22
            },
            {
              "seed": 14,
              "name": "N. Dakota State",
              "row": 24
            }
          ],
          [
            {
              "seed": 7,
              "name": "UCLA",
              "row": 26
            },
            {
              "seed": 10,
              "name": "UCF",
              "row": 28
            }
          ],
          [
            {
              "seed": 2,
              "name": "UConn",
              "row": 30
            },
            {
              "seed": 15,
              "name": "Furman",
              "row": 32
            }
          ]
        ],
        "round_winners": {
          "Round of 32": [
            "Duke",
            "TCU",
            "Louisville",
            "Michigan State"
          ],
          "Sweet 16": [],
          "Elite 8": [],
          "Final Four": [],
          "Finalist": [],
          "Champion": []
        },
        "name": "South"
      },
      {
        "matchups": [
          [
            {
              "seed": 1,
              "name": "Arizona",
              "row": 2
            },
            {
              "seed": 16,
              "name": "LIU",
              "row": 4
            }
          ],
          [
            {
              "seed": 8,
              "name": "Villanova",
              "row": 6
            },
            {
              "seed": 9,
              "name": "Utah State",
              "row": 8
            }
          ],
          [
            {
              "seed": 5,
              "name": "Wisconsin",
              "row": 10
            },
            {
              "seed": 12,
              "name": "High Point",
              "row": 12
            }
          ],
          [
            {
              "seed": 4,
              "name": "Arkansas",
              "row": 14
            },
            {
              "seed": 13,
              "name": "Hawaii",
              "row": 16
            }
          ],
          [
            {
              "seed": 6,
              "name": "BYU",
              "row": 18
            },
            {
              "seed": 11,
              "name": "TX/NC State",
              "row": 20
            }
          ],
          [
            {
              "seed": 3,
              "name": "Gonzaga",
              "row": 22
            },
            {
              "seed": 14,
              "name": "Kennesaw State",
              "row": 24
            }
          ],
          [
            {
              "seed": 7,
              "name": "Miami (FL)",
              "row": 26
            },
            {
              "seed": 10,
              "name": "Missouri",
              "row": 28
            }
          ],
          [
            {
              "seed": 2,
              "name": "Purdue",
              "row": 30
            },
            {
              "seed": 15,
              "name": "Queens",
              "row": 32
            }
          ]
        ],
        "round_winners": {
          "Round of 32": [
            "Arizona",
            "High Point",
            "Arkansas",
            "TX/NC State",
            "Gonzaga"
          ],
          "Sweet 16": [],
          "Elite 8": [],
          "Final Four": [],
          "Finalist": []
        },
        "name": "East"
      },
      {
        "matchups": [
          [
            {
              "seed": 1,
              "name": "Florida",
              "row": 35
            },
            {
              "seed": 16,
              "name": "PV A&M/Lehigh",
              "row": 37
            }
          ],
          [
            {
              "seed": 8,
              "name": "Clemson",
              "row": 39
            },
            {
              "seed": 9,
              "name": "Iowa",
              "row": 41
            }
          ],
          [
            {
              "seed": 5,
              "name": "Vanderbilt",
              "row": 43
            },
            {
              "seed": 12,
              "name": "McNeese",
              "row": 45
            }
          ],
          [
            {
              "seed": 4,
              "name": "Nebraska",
              "row": 47
            },
            {
              "seed": 13,
              "name": "Troy",
              "row": 49
            }
          ],
          [
            {
              "seed": 6,
              "name": "North Carolina",
              "row": 51
            },
            {
              "seed": 11,
              "name": "VCU",
              "row": 53
            }
          ],
          [
            {
              "seed": 3,
              "name": "Illinois",
              "row": 55
            },
            {
              "seed": 14,
              "name": "Penn",
              "row": 57
            }
          ],
          [
            {
              "seed": 7,
              "name": "Saint Mary's",
              "row": 59
            },
            {
              "seed": 10,
              "name": "Texas A&M",
              "row": 61
            }
          ],
          [
            {
              "seed": 2,
              "name": "Houston",
              "row": 63
            },
            {
              "seed": 15,
              "name": "Idaho",
              "row": 65
            }
          ]
        ],
        "round_winners": {
          "Round of 32": [
            "Vanderbilt",
            "Nebraska",
            "VCU",
            "Illinois",
            "Texas A&M",
            "Houston"
          ],
          "Sweet 16": [],
          "Elite 8": [],
          "Final Four": [],
          "Finalist": [],
          "Champion": []
        },
        "name": "West"
      },
      {
        "matchups": [
          [
            {
              "seed": 1,
              "name": "Michigan",
              "row": 35
            },
            {
              "seed": 16,
              "name": "UMBC/Howard",
              "row": 37
            }
          ],
          [
            {
              "seed": 8,
              "name": "Georgia",
              "row": 39
            },
            {
              "seed": 9,
              "name": "Saint Louis",
              "row": 41
            }
          ],
          [
            {
              "seed": 5,
              "name": "Texas Tech",
              "row": 43
            },
            {
              "seed": 12,
              "name": "Akron",
              "row": 45
            }
          ],
          [
            {
              "seed": 4,
              "name": "Alabama",
              "row": 47
            },
            {
              "seed": 13,
              "name": "Hofstra",
              "row": 49
            }
          ],
          [
            {
              "seed": 6,
              "name": "Tennessee",
              "row": 51
            },
            {
              "seed": 11,
              "name": "SMU/Miami OH",
              "row": 53
            }
          ],
          [
            {
              "seed": 3,
              "name": "Virginia",
              "row": 55
            },
            {
              "seed": 14,
              "name": "Wright State",
              "row": 57
            }
          ],
          [
            {
              "seed": 7,
              "name": "Kentucky",
              "row": 59
            },
            {
              "seed": 10,
              "name": "Santa Clara",
              "row": 61
            }
          ],
          [
            {
              "seed": 2,
              "name": "Iowa State",
              "row": 63
            },
            {
              "seed": 15,
              "name": "Tennessee State",
              "row": 65
            }
          ]
        ],
        "round_winners": {
          "Round of 32": [
            "Michigan",
            "Saint Louis",
            "Texas Tech",
            "Kentucky",
            "Iowa State",
            "Virginia",
            "Alabama"
          ],
          "Sweet 16": [],
          "Elite 8": [],
          "Final Four": [],
          "Finalist": []
        },
        "name": "Midwest"
      }
    ]
  },
  "participants": [
    {
      "id": "dad",
      "name": "Dad",
      "tiebreaker": "62 - 58",
      "score": 16,
      "regions": [
        {
          "matchups": [
            [
              {
                "seed": 1,
                "name": "Duke",
                "row": 2
              },
              {
                "seed": 16,
                "name": "Siena",
                "row": 4
              }
            ],
            [
              {
                "seed": 8,
                "name": "Ohio State",
                "row": 6
              },
              {
                "seed": 9,
                "name": "TCU",
                "row": 8
              }
            ],
            [
              {
                "seed": 5,
                "name": "St. John's",
                "row": 10
              },
              {
                "seed": 12,
                "name": "Northern Iowa",
                "row": 12
              }
            ],
            [
              {
                "seed": 4,
                "name": "Kansas",
                "row": 14
              },
              {
                "seed": 13,
                "name": "Cal Baptist",
                "row": 16
              }
            ],
            [
              {
                "seed": 6,
                "name": "Louisville",
                "row": 18
              },
              {
                "seed": 11,
                "name": "South Florida",
                "row": 20
              }
            ],
            [
              {
                "seed": 3,
                "name": "Michigan State",
                "row": 22
              },
              {
                "seed": 14,
                "name": "N. Dakota State",
                "row": 24
              }
            ],
            [
              {
                "seed": 7,
                "name": "UCLA",
                "row": 26
              },
              {
                "seed": 10,
                "name": "UCF",
                "row": 28
              }
            ],
            [
              {
                "seed": 2,
                "name": "UConn",
                "row": 30
              },
              {
                "seed": 15,
                "name": "Furman",
                "row": 32
              }
            ]
          ],
          "round_winners": {
            "Round of 32": [
              "Duke",
              "Ohio State",
              "St. John's",
              "Kansas",
              "Louisville",
              "Michigan State",
              "UCLA",
              "UConn"
            ],
            "Sweet 16": [
              "Duke",
              "St. John's",
              "Michigan State",
              "UConn"
            ],
            "Elite 8": [
              "Duke",
              "UConn"
            ],
            "Final Four": [
              "Duke"
            ],
            "Finalist": [
              "Duke"
            ],
            "Champion": [
              "Michigan"
            ]
          },
          "name": "South"
        },
        {
          "matchups": [
            [
              {
                "seed": 1,
                "name": "Arizona",
                "row": 2
              },
              {
                "seed": 16,
                "name": "LIU",
                "row": 4
              }
            ],
            [
              {
                "seed": 8,
                "name": "Villanova",
                "row": 6
              },
              {
                "seed": 9,
                "name": "Utah State",
                "row": 8
              }
            ],
            [
              {
                "seed": 5,
                "name": "Wisconsin",
                "row": 10
              },
              {
                "seed": 12,
                "name": "High Point",
                "row": 12
              }
            ],
            [
              {
                "seed": 4,
                "name": "Arkansas",
                "row": 14
              },
              {
                "seed": 13,
                "name": "Hawaii",
                "row": 16
              }
            ],
            [
              {
                "seed": 6,
                "name": "BYU",
                "row": 18
              },
              {
                "seed": 11,
                "name": "TX/NC State",
                "row": 20
              }
            ],
            [
              {
                "seed": 3,
                "name": "Gonzaga",
                "row": 22
              },
              {
                "seed": 14,
                "name": "Kennesaw State",
                "row": 24
              }
            ],
            [
              {
                "seed": 7,
                "name": "Miami (FL)",
                "row": 26
              },
              {
                "seed": 10,
                "name": "Missouri",
                "row": 28
              }
            ],
            [
              {
                "seed": 2,
                "name": "Purdue",
                "row": 30
              },
              {
                "seed": 15,
                "name": "Queens",
                "row": 32
              }
            ]
          ],
          "round_winners": {
            "Round of 32": [
              "Arizona",
              "Utah State",
              "Wisconsin",
              "Arkansas",
              "BYU",
              "Gonzaga",
              "Miami (FL)",
              "Purdue"
            ],
            "Sweet 16": [
              "Arizona",
              "Arkansas",
              "Gonzaga",
              "Purdue"
            ],
            "Elite 8": [
              "Arizona",
              "Purdue"
            ],
            "Final Four": [
              "Arizona"
            ],
            "Finalist": [
              "Michigan"
            ]
          },
          "name": "East"
        },
        {
          "matchups": [
            [
              {
                "seed": 1,
                "name": "Florida",
                "row": 35
              },
              {
                "seed": 16,
                "name": "PV A&M/Lehigh",
                "row": 37
              }
            ],
            [
              {
                "seed": 8,
                "name": "Clemson",
                "row": 39
              },
              {
                "seed": 9,
                "name": "Iowa",
                "row": 41
              }
            ],
            [
              {
                "seed": 5,
                "name": "Vanderbilt",
                "row": 43
              },
              {
                "seed": 12,
                "name": "McNeese",
                "row": 45
              }
            ],
            [
              {
                "seed": 4,
                "name": "Nebraska",
                "row": 47
              },
              {
                "seed": 13,
                "name": "Troy",
                "row": 49
              }
            ],
            [
              {
                "seed": 6,
                "name": "North Carolina",
                "row": 51
              },
              {
                "seed": 11,
                "name": "VCU",
                "row": 53
              }
            ],
            [
              {
                "seed": 3,
                "name": "Illinois",
                "row": 55
              },
              {
                "seed": 14,
                "name": "Penn",
                "row": 57
              }
            ],
            [
              {
                "seed": 7,
                "name": "Saint Mary's",
                "row": 59
              },
              {
                "seed": 10,
                "name": "Texas A&M",
                "row": 61
              }
            ],
            [
              {
                "seed": 2,
                "name": "Houston",
                "row": 63
              },
              {
                "seed": 15,
                "name": "Idaho",
                "row": 65
              }
            ]
          ],
          "round_winners": {
            "Round of 32": [
              "Florida",
              "Iowa",
              "Vanderbilt",
              "Nebraska",
              "North Carolina",
              "Illinois",
              "Saint Mary's",
              "Houston"
            ],
            "Sweet 16": [
              "Florida",
              "Vanderbilt",
              "Illinois",
              "Houston"
            ],
            "Elite 8": [
              "Florida",
              "Illinois"
            ],
            "Final Four": [
              "Illinois"
            ],
            "Finalist": [],
            "Champion": []
          },
          "name": "West"
        },
        {
          "matchups": [
            [
              {
                "seed": 1,
                "name": "Michigan",
                "row": 35
              },
              {
                "seed": 16,
                "name": "UMBC/Howard",
                "row": 37
              }
            ],
            [
              {
                "seed": 8,
                "name": "Georgia",
                "row": 39
              },
              {
                "seed": 9,
                "name": "Saint Louis",
                "row": 41
              }
            ],
            [
              {
                "seed": 5,
                "name": "Texas Tech",
                "row": 43
              },
              {
                "seed": 12,
                "name": "Akron",
                "row": 45
              }
            ],
            [
              {
                "seed": 4,
                "name": "Alabama",
                "row": 47
              },
              {
                "seed": 13,
                "name": "Hofstra",
                "row": 49
              }
            ],
            [
              {
                "seed": 6,
                "name": "Tennessee",
                "row": 51
              },
              {
                "seed": 11,
                "name": "SMU/Miami OH",
                "row": 53
              }
            ],
            [
              {
                "seed": 3,
                "name": "Virginia",
                "row": 55
              },
              {
                "seed": 14,
                "name": "Wright State",
                "row": 57
              }
            ],
            [
              {
                "seed": 7,
                "name": "Kentucky",
                "row": 59
              },
              {
                "seed": 10,
                "name": "Santa Clara",
                "row": 61
              }
            ],
            [
              {
                "seed": 2,
                "name": "Iowa State",
                "row": 63
              },
              {
                "seed": 15,
                "name": "Tennessee State",
                "row": 65
              }
            ]
          ],
          "round_winners": {
            "Round of 32": [
              "Michigan",
              "Georgia",
              "Texas Tech",
              "Alabama",
              "Tennessee",
              "Virginia",
              "Kentucky",
              "Iowa State"
            ],
            "Sweet 16": [
              "Michigan",
              "Alabama",
              "Virginia",
              "Iowa State"
            ],
            "Elite 8": [
              "Michigan",
              "Iowa State"
            ],
            "Final Four": [
              "Michigan"
            ],
            "Finalist": []
          },
          "name": "Midwest"
        }
      ]
    },
    {
      "id": "mom",
      "name": "Mom",
      "tiebreaker": "62 - 51",
      "score": 18,
      "regions": [
        {
          "matchups": [
            [
              {
                "seed": 1,
                "name": "Duke",
                "row": 2
              },
              {
                "seed": 16,
                "name": "Siena",
                "row": 4
              }
            ],
            [
              {
                "seed": 8,
                "name": "Ohio State",
                "row": 6
              },
              {
                "seed": 9,
                "name": "TCU",
                "row": 8
              }
            ],
            [
              {
                "seed": 5,
                "name": "St. John's",
                "row": 10
              },
              {
                "seed": 12,
                "name": "Northern Iowa",
                "row": 12
              }
            ],
            [
              {
                "seed": 4,
                "name": "Kansas",
                "row": 14
              },
              {
                "seed": 13,
                "name": "Cal Baptist",
                "row": 16
              }
            ],
            [
              {
                "seed": 6,
                "name": "Louisville",
                "row": 18
              },
              {
                "seed": 11,
                "name": "South Florida",
                "row": 20
              }
            ],
            [
              {
                "seed": 3,
                "name": "Michigan State",
                "row": 22
              },
              {
                "seed": 14,
                "name": "N. Dakota State",
                "row": 24
              }
            ],
            [
              {
                "seed": 7,
                "name": "UCLA",
                "row": 26
              },
              {
                "seed": 10,
                "name": "UCF",
                "row": 28
              }
            ],
            [
              {
                "seed": 2,
                "name": "UConn",
                "row": 30
              },
              {
                "seed": 15,
                "name": "Furman",
                "row": 32
              }
            ]
          ],
          "round_winners": {
            "Round of 32": [
              "Duke",
              "TCU",
              "St. John's",
              "Kansas",
              "South Florida",
              "Michigan State",
              "UCLA",
              "UConn"
            ],
            "Sweet 16": [
              "Duke",
              "Kansas",
              "South Florida",
              "UConn"
            ],
            "Elite 8": [
              "Duke",
              "UConn"
            ],
            "Final Four": [
              "Duke"
            ],
            "Finalist": [
              "Duke"
            ],
            "Champion": [
              "Arizona"
            ]
          },
          "name": "South"
        },
        {
          "matchups": [
            [
              {
                "seed": 1,
                "name": "Arizona",
                "row": 2
              },
              {
                "seed": 16,
                "name": "LIU",
                "row": 4
              }
            ],
            [
              {
                "seed": 8,
                "name": "Villanova",
                "row": 6
              },
              {
                "seed": 9,
                "name": "Utah State",
                "row": 8
              }
            ],
            [
              {
                "seed": 5,
                "name": "Wisconsin",
                "row": 10
              },
              {
                "seed": 12,
                "name": "High Point",
                "row": 12
              }
            ],
            [
              {
                "seed": 4,
                "name": "Arkansas",
                "row": 14
              },
              {
                "seed": 13,
                "name": "Hawaii",
                "row": 16
              }
            ],
            [
              {
                "seed": 6,
                "name": "BYU",
                "row": 18
              },
              {
                "seed": 11,
                "name": "TX/NC State",
                "row": 20
              }
            ],
            [
              {
                "seed": 3,
                "name": "Gonzaga",
                "row": 22
              },
              {
                "seed": 14,
                "name": "Kennesaw State",
                "row": 24
              }
            ],
            [
              {
                "seed": 7,
                "name": "Miami (FL)",
                "row": 26
              },
              {
                "seed": 10,
                "name": "Missouri",
                "row": 28
              }
            ],
            [
              {
                "seed": 2,
                "name": "Purdue",
                "row": 30
              },
              {
                "seed": 15,
                "name": "Queens",
                "row": 32
              }
            ]
          ],
          "round_winners": {
            "Round of 32": [
              "Arizona",
              "Villanova",
              "Wisconsin",
              "Arkansas",
              "BYU",
              "Gonzaga",
              "Miami (FL)",
              "Purdue"
            ],
            "Sweet 16": [
              "Arizona",
              "Wisconsin",
              "Gonzaga",
              "Purdue"
            ],
            "Elite 8": [
              "Arizona",
              "Purdue"
            ],
            "Final Four": [
              "Arizona"
            ],
            "Finalist": [
              "Arizona"
            ]
          },
          "name": "East"
        },
        {
          "matchups": [
            [
              {
                "seed": 1,
                "name": "Florida",
                "row": 35
              },
              {
                "seed": 16,
                "name": "PV A&M/Lehigh",
                "row": 37
              }
            ],
            [
              {
                "seed": 8,
                "name": "Clemson",
                "row": 39
              },
              {
                "seed": 9,
                "name": "Iowa",
                "row": 41
              }
            ],
            [
              {
                "seed": 5,
                "name": "Vanderbilt",
                "row": 43
              },
              {
                "seed": 12,
                "name": "McNeese",
                "row": 45
              }
            ],
            [
              {
                "seed": 4,
                "name": "Nebraska",
                "row": 47
              },
              {
                "seed": 13,
                "name": "Troy",
                "row": 49
              }
            ],
            [
              {
                "seed": 6,
                "name": "North Carolina",
                "row": 51
              },
              {
                "seed": 11,
                "name": "VCU",
                "row": 53
              }
            ],
            [
              {
                "seed": 3,
                "name": "Illinois",
                "row": 55
              },
              {
                "seed": 14,
                "name": "Penn",
                "row": 57
              }
            ],
            [
              {
                "seed": 7,
                "name": "Saint Mary's",
                "row": 59
              },
              {
                "seed": 10,
                "name": "Texas A&M",
                "row": 61
              }
            ],
            [
              {
                "seed": 2,
                "name": "Houston",
                "row": 63
              },
              {
                "seed": 15,
                "name": "Idaho",
                "row": 65
              }
            ]
          ],
          "round_winners": {
            "Round of 32": [
              "Florida",
              "Clemson",
              "Vanderbilt",
              "Nebraska",
              "North Carolina",
              "Illinois",
              "Texas A&M",
              "Houston"
            ],
            "Sweet 16": [
              "Florida",
              "Vanderbilt",
              "Illinois",
              "Houston"
            ],
            "Elite 8": [
              "Florida",
              "Houston"
            ],
            "Final Four": [
              "Florida"
            ],
            "Finalist": [],
            "Champion": []
          },
          "name": "West"
        },
        {
          "matchups": [
            [
              {
                "seed": 1,
                "name": "Michigan",
                "row": 35
              },
              {
                "seed": 16,
                "name": "UMBC/Howard",
                "row": 37
              }
            ],
            [
              {
                "seed": 8,
                "name": "Georgia",
                "row": 39
              },
              {
                "seed": 9,
                "name": "Saint Louis",
                "row": 41
              }
            ],
            [
              {
                "seed": 5,
                "name": "Texas Tech",
                "row": 43
              },
              {
                "seed": 12,
                "name": "Akron",
                "row": 45
              }
            ],
            [
              {
                "seed": 4,
                "name": "Alabama",
                "row": 47
              },
              {
                "seed": 13,
                "name": "Hofstra",
                "row": 49
              }
            ],
            [
              {
                "seed": 6,
                "name": "Tennessee",
                "row": 51
              },
              {
                "seed": 11,
                "name": "SMU/Miami OH",
                "row": 53
              }
            ],
            [
              {
                "seed": 3,
                "name": "Virginia",
                "row": 55
              },
              {
                "seed": 14,
                "name": "Wright State",
                "row": 57
              }
            ],
            [
              {
                "seed": 7,
                "name": "Kentucky",
                "row": 59
              },
              {
                "seed": 10,
                "name": "Santa Clara",
                "row": 61
              }
            ],
            [
              {
                "seed": 2,
                "name": "Iowa State",
                "row": 63
              },
              {
                "seed": 15,
                "name": "Tennessee State",
                "row": 65
              }
            ]
          ],
          "round_winners": {
            "Round of 32": [
              "Michigan",
              "Saint Louis",
              "Texas Tech",
              "Alabama",
              "Tennessee",
              "Virginia",
              "Kentucky",
              "Iowa State"
            ],
            "Sweet 16": [
              "Michigan",
              "Alabama",
              "Virginia",
              "Kentucky"
            ],
            "Elite 8": [
              "Michigan",
              "Virginia"
            ],
            "Final Four": [
              "Michigan"
            ],
            "Finalist": []
          },
          "name": "Midwest"
        }
      ]
    },
    {
      "id": "jared",
      "name": "Jared",
      "tiebreaker": "80-75",
      "score": 18,
      "regions": [
        {
          "matchups": [
            [
              {
                "seed": 1,
                "name": "Duke",
                "row": 2
              },
              {
                "seed": 16,
                "name": "Siena",
                "row": 4
              }
            ],
            [
              {
                "seed": 8,
                "name": "Ohio State",
                "row": 6
              },
              {
                "seed": 9,
                "name": "TCU",
                "row": 8
              }
            ],
            [
              {
                "seed": 5,
                "name": "St. John's",
                "row": 10
              },
              {
                "seed": 12,
                "name": "Northern Iowa",
                "row": 12
              }
            ],
            [
              {
                "seed": 4,
                "name": "Kansas",
                "row": 14
              },
              {
                "seed": 13,
                "name": "Cal Baptist",
                "row": 16
              }
            ],
            [
              {
                "seed": 6,
                "name": "Louisville",
                "row": 18
              },
              {
                "seed": 11,
                "name": "South Florida",
                "row": 20
              }
            ],
            [
              {
                "seed": 3,
                "name": "Michigan State",
                "row": 22
              },
              {
                "seed": 14,
                "name": "N. Dakota State",
                "row": 24
              }
            ],
            [
              {
                "seed": 7,
                "name": "UCLA",
                "row": 26
              },
              {
                "seed": 10,
                "name": "UCF",
                "row": 28
              }
            ],
            [
              {
                "seed": 2,
                "name": "UConn",
                "row": 30
              },
              {
                "seed": 15,
                "name": "Furman",
                "row": 32
              }
            ]
          ],
          "round_winners": {
            "Round of 32": [
              "Duke",
              "Ohio State",
              "St. John's",
              "Kansas",
              "South Florida",
              "Michigan State",
              "UCLA",
              "UConn"
            ],
            "Sweet 16": [
              "Duke",
              "Kansas",
              "Michigan State",
              "UConn"
            ],
            "Elite 8": [
              "Duke",
              "UConn"
            ],
            "Final Four": [
              "Duke"
            ],
            "Finalist": [
              "Duke"
            ],
            "Champion": [
              "Arizona"
            ]
          },
          "name": "South"
        },
        {
          "matchups": [
            [
              {
                "seed": 1,
                "name": "Arizona",
                "row": 2
              },
              {
                "seed": 16,
                "name": "LIU",
                "row": 4
              }
            ],
            [
              {
                "seed": 8,
                "name": "Villanova",
                "row": 6
              },
              {
                "seed": 9,
                "name": "Utah State",
                "row": 8
              }
            ],
            [
              {
                "seed": 5,
                "name": "Wisconsin",
                "row": 10
              },
              {
                "seed": 12,
                "name": "High Point",
                "row": 12
              }
            ],
            [
              {
                "seed": 4,
                "name": "Arkansas",
                "row": 14
              },
              {
                "seed": 13,
                "name": "Hawaii",
                "row": 16
              }
            ],
            [
              {
                "seed": 6,
                "name": "BYU",
                "row": 18
              },
              {
                "seed": 11,
                "name": "TX/NC State",
                "row": 20
              }
            ],
            [
              {
                "seed": 3,
                "name": "Gonzaga",
                "row": 22
              },
              {
                "seed": 14,
                "name": "Kennesaw State",
                "row": 24
              }
            ],
            [
              {
                "seed": 7,
                "name": "Miami (FL)",
                "row": 26
              },
              {
                "seed": 10,
                "name": "Missouri",
                "row": 28
              }
            ],
            [
              {
                "seed": 2,
                "name": "Purdue",
                "row": 30
              },
              {
                "seed": 15,
                "name": "Queens",
                "row": 32
              }
            ]
          ],
          "round_winners": {
            "Round of 32": [
              "Arizona",
              "Villanova",
              "Wisconsin",
              "Arkansas",
              "TX/NC State",
              "Gonzaga",
              "Miami (FL)",
              "Purdue"
            ],
            "Sweet 16": [
              "Arizona",
              "Arkansas",
              "Gonzaga",
              "Purdue"
            ],
            "Elite 8": [
              "Arizona",
              "Purdue"
            ],
            "Final Four": [
              "Arizona"
            ],
            "Finalist": [
              "Arizona"
            ]
          },
          "name": "East"
        },
        {
          "matchups": [
            [
              {
                "seed": 1,
                "name": "Florida",
                "row": 35
              },
              {
                "seed": 16,
                "name": "PV A&M/Lehigh",
                "row": 37
              }
            ],
            [
              {
                "seed": 8,
                "name": "Clemson",
                "row": 39
              },
              {
                "seed": 9,
                "name": "Iowa",
                "row": 41
              }
            ],
            [
              {
                "seed": 5,
                "name": "Vanderbilt",
                "row": 43
              },
              {
                "seed": 12,
                "name": "McNeese",
                "row": 45
              }
            ],
            [
              {
                "seed": 4,
                "name": "Nebraska",
                "row": 47
              },
              {
                "seed": 13,
                "name": "Troy",
                "row": 49
              }
            ],
            [
              {
                "seed": 6,
                "name": "North Carolina",
                "row": 51
              },
              {
                "seed": 11,
                "name": "VCU",
                "row": 53
              }
            ],
            [
              {
                "seed": 3,
                "name": "Illinois",
                "row": 55
              },
              {
                "seed": 14,
                "name": "Penn",
                "row": 57
              }
            ],
            [
              {
                "seed": 7,
                "name": "Saint Mary's",
                "row": 59
              },
              {
                "seed": 10,
                "name": "Texas A&M",
                "row": 61
              }
            ],
            [
              {
                "seed": 2,
                "name": "Houston",
                "row": 63
              },
              {
                "seed": 15,
                "name": "Idaho",
                "row": 65
              }
            ]
          ],
          "round_winners": {
            "Round of 32": [
              "Florida",
              "Clemson",
              "Vanderbilt",
              "Nebraska",
              "North Carolina",
              "Illinois",
              "Texas A&M",
              "Houston"
            ],
            "Sweet 16": [
              "Florida",
              "Vanderbilt",
              "Illinois",
              "Houston"
            ],
            "Elite 8": [
              "Florida",
              "Illinois"
            ],
            "Final Four": [
              "Florida"
            ],
            "Finalist": [],
            "Champion": []
          },
          "name": "West"
        },
        {
          "matchups": [
            [
              {
                "seed": 1,
                "name": "Michigan",
                "row": 35
              },
              {
                "seed": 16,
                "name": "UMBC/Howard",
                "row": 37
              }
            ],
            [
              {
                "seed": 8,
                "name": "Georgia",
                "row": 39
              },
              {
                "seed": 9,
                "name": "Saint Louis",
                "row": 41
              }
            ],
            [
              {
                "seed": 5,
                "name": "Texas Tech",
                "row": 43
              },
              {
                "seed": 12,
                "name": "Akron",
                "row": 45
              }
            ],
            [
              {
                "seed": 4,
                "name": "Alabama",
                "row": 47
              },
              {
                "seed": 13,
                "name": "Hofstra",
                "row": 49
              }
            ],
            [
              {
                "seed": 6,
                "name": "Tennessee",
                "row": 51
              },
              {
                "seed": 11,
                "name": "SMU/Miami OH",
                "row": 53
              }
            ],
            [
              {
                "seed": 3,
                "name": "Virginia",
                "row": 55
              },
              {
                "seed": 14,
                "name": "Wright State",
                "row": 57
              }
            ],
            [
              {
                "seed": 7,
                "name": "Kentucky",
                "row": 59
              },
              {
                "seed": 10,
                "name": "Santa Clara",
                "row": 61
              }
            ],
            [
              {
                "seed": 2,
                "name": "Iowa State",
                "row": 63
              },
              {
                "seed": 15,
                "name": "Tennessee State",
                "row": 65
              }
            ]
          ],
          "round_winners": {
            "Round of 32": [
              "Michigan",
              "Saint Louis",
              "Texas Tech",
              "Alabama",
              "Tennessee",
              "Virginia",
              "Kentucky",
              "Iowa State"
            ],
            "Sweet 16": [
              "Michigan",
              "Alabama",
              "Virginia",
              "Iowa State"
            ],
            "Elite 8": [
              "Michigan",
              "Iowa State"
            ],
            "Final Four": [
              "Michigan"
            ],
            "Finalist": []
          },
          "name": "Midwest"
        }
      ]
    },
    {
      "id": "megan",
      "name": "Megan",
      "tiebreaker": "82-74",
      "score": 20,
      "regions": [
        {
          "matchups": [
            [
              {
                "seed": 1,
                "name": "Duke",
                "row": 2
              },
              {
                "seed": 16,
                "name": "Siena",
                "row": 4
              }
            ],
            [
              {
                "seed": 8,
                "name": "Ohio State",
                "row": 6
              },
              {
                "seed": 9,
                "name": "TCU",
                "row": 8
              }
            ],
            [
              {
                "seed": 5,
                "name": "St. John's",
                "row": 10
              },
              {
                "seed": 12,
                "name": "Northern Iowa",
                "row": 12
              }
            ],
            [
              {
                "seed": 4,
                "name": "Kansas",
                "row": 14
              },
              {
                "seed": 13,
                "name": "Cal Baptist",
                "row": 16
              }
            ],
            [
              {
                "seed": 6,
                "name": "Louisville",
                "row": 18
              },
              {
                "seed": 11,
                "name": "South Florida",
                "row": 20
              }
            ],
            [
              {
                "seed": 3,
                "name": "Michigan State",
                "row": 22
              },
              {
                "seed": 14,
                "name": "N. Dakota State",
                "row": 24
              }
            ],
            [
              {
                "seed": 7,
                "name": "UCLA",
                "row": 26
              },
              {
                "seed": 10,
                "name": "UCF",
                "row": 28
              }
            ],
            [
              {
                "seed": 2,
                "name": "UConn",
                "row": 30
              },
              {
                "seed": 15,
                "name": "Furman",
                "row": 32
              }
            ]
          ],
          "round_winners": {
            "Round of 32": [
              "Duke",
              "TCU",
              "St. John's",
              "Kansas",
              "Louisville",
              "Michigan State",
              "UCF",
              "UConn"
            ],
            "Sweet 16": [
              "Duke",
              "Kansas",
              "Michigan State",
              "UConn"
            ],
            "Elite 8": [
              "Duke",
              "UConn"
            ],
            "Final Four": [
              "Duke"
            ],
            "Finalist": [
              "Florida"
            ],
            "Champion": [
              "Arizona"
            ]
          },
          "name": "South"
        },
        {
          "matchups": [
            [
              {
                "seed": 1,
                "name": "Arizona",
                "row": 2
              },
              {
                "seed": 16,
                "name": "LIU",
                "row": 4
              }
            ],
            [
              {
                "seed": 8,
                "name": "Villanova",
                "row": 6
              },
              {
                "seed": 9,
                "name": "Utah State",
                "row": 8
              }
            ],
            [
              {
                "seed": 5,
                "name": "Wisconsin",
                "row": 10
              },
              {
                "seed": 12,
                "name": "High Point",
                "row": 12
              }
            ],
            [
              {
                "seed": 4,
                "name": "Arkansas",
                "row": 14
              },
              {
                "seed": 13,
                "name": "Hawaii",
                "row": 16
              }
            ],
            [
              {
                "seed": 6,
                "name": "BYU",
                "row": 18
              },
              {
                "seed": 11,
                "name": "TX/NC State",
                "row": 20
              }
            ],
            [
              {
                "seed": 3,
                "name": "Gonzaga",
                "row": 22
              },
              {
                "seed": 14,
                "name": "Kennesaw State",
                "row": 24
              }
            ],
            [
              {
                "seed": 7,
                "name": "Miami (FL)",
                "row": 26
              },
              {
                "seed": 10,
                "name": "Missouri",
                "row": 28
              }
            ],
            [
              {
                "seed": 2,
                "name": "Purdue",
                "row": 30
              },
              {
                "seed": 15,
                "name": "Queens",
                "row": 32
              }
            ]
          ],
          "round_winners": {
            "Round of 32": [
              "Arizona",
              "Villanova",
              "Wisconsin",
              "Arkansas",
              "TX/NC State",
              "Gonzaga",
              "Miami (FL)",
              "Purdue"
            ],
            "Sweet 16": [
              "Arizona",
              "Wisconsin",
              "Gonzaga",
              "Purdue"
            ],
            "Elite 8": [
              "Arizona",
              "Gonzaga"
            ],
            "Final Four": [
              "Arizona"
            ],
            "Finalist": [
              "Arizona"
            ]
          },
          "name": "East"
        },
        {
          "matchups": [
            [
              {
                "seed": 1,
                "name": "Florida",
                "row": 35
              },
              {
                "seed": 16,
                "name": "PV A&M/Lehigh",
                "row": 37
              }
            ],
            [
              {
                "seed": 8,
                "name": "Clemson",
                "row": 39
              },
              {
                "seed": 9,
                "name": "Iowa",
                "row": 41
              }
            ],
            [
              {
                "seed": 5,
                "name": "Vanderbilt",
                "row": 43
              },
              {
                "seed": 12,
                "name": "McNeese",
                "row": 45
              }
            ],
            [
              {
                "seed": 4,
                "name": "Nebraska",
                "row": 47
              },
              {
                "seed": 13,
                "name": "Troy",
                "row": 49
              }
            ],
            [
              {
                "seed": 6,
                "name": "North Carolina",
                "row": 51
              },
              {
                "seed": 11,
                "name": "VCU",
                "row": 53
              }
            ],
            [
              {
                "seed": 3,
                "name": "Illinois",
                "row": 55
              },
              {
                "seed": 14,
                "name": "Penn",
                "row": 57
              }
            ],
            [
              {
                "seed": 7,
                "name": "Saint Mary's",
                "row": 59
              },
              {
                "seed": 10,
                "name": "Texas A&M",
                "row": 61
              }
            ],
            [
              {
                "seed": 2,
                "name": "Houston",
                "row": 63
              },
              {
                "seed": 15,
                "name": "Idaho",
                "row": 65
              }
            ]
          ],
          "round_winners": {
            "Round of 32": [
              "Florida",
              "Clemson",
              "Vanderbilt",
              "Nebraska",
              "North Carolina",
              "Illinois",
              "Texas A&M",
              "Houston"
            ],
            "Sweet 16": [
              "Florida",
              "Vanderbilt",
              "Illinois",
              "Houston"
            ],
            "Elite 8": [
              "Florida",
              "Houston"
            ],
            "Final Four": [
              "Florida"
            ],
            "Finalist": [],
            "Champion": []
          },
          "name": "West"
        },
        {
          "matchups": [
            [
              {
                "seed": 1,
                "name": "Michigan",
                "row": 35
              },
              {
                "seed": 16,
                "name": "UMBC/Howard",
                "row": 37
              }
            ],
            [
              {
                "seed": 8,
                "name": "Georgia",
                "row": 39
              },
              {
                "seed": 9,
                "name": "Saint Louis",
                "row": 41
              }
            ],
            [
              {
                "seed": 5,
                "name": "Texas Tech",
                "row": 43
              },
              {
                "seed": 12,
                "name": "Akron",
                "row": 45
              }
            ],
            [
              {
                "seed": 4,
                "name": "Alabama",
                "row": 47
              },
              {
                "seed": 13,
                "name": "Hofstra",
                "row": 49
              }
            ],
            [
              {
                "seed": 6,
                "name": "Tennessee",
                "row": 51
              },
              {
                "seed": 11,
                "name": "SMU/Miami OH",
                "row": 53
              }
            ],
            [
              {
                "seed": 3,
                "name": "Virginia",
                "row": 55
              },
              {
                "seed": 14,
                "name": "Wright State",
                "row": 57
              }
            ],
            [
              {
                "seed": 7,
                "name": "Kentucky",
                "row": 59
              },
              {
                "seed": 10,
                "name": "Santa Clara",
                "row": 61
              }
            ],
            [
              {
                "seed": 2,
                "name": "Iowa State",
                "row": 63
              },
              {
                "seed": 15,
                "name": "Tennessee State",
                "row": 65
              }
            ]
          ],
          "round_winners": {
            "Round of 32": [
              "Michigan",
              "Saint Louis",
              "Texas Tech",
              "Alabama",
              "Tennessee",
              "Virginia",
              "Kentucky",
              "Iowa State"
            ],
            "Sweet 16": [
              "Michigan",
              "Texas Tech",
              "Virginia",
              "Iowa State"
            ],
            "Elite 8": [
              "Michigan",
              "Iowa State"
            ],
            "Final Four": [
              "Michigan"
            ],
            "Finalist": []
          },
          "name": "Midwest"
        }
      ]
    },
    {
      "id": "lauren",
      "name": "Lauren",
      "tiebreaker": "85 - 78",
      "score": 16,
      "regions": [
        {
          "matchups": [
            [
              {
                "seed": 1,
                "name": "Duke",
                "row": 2
              },
              {
                "seed": 16,
                "name": "Siena",
                "row": 4
              }
            ],
            [
              {
                "seed": 8,
                "name": "Ohio State",
                "row": 6
              },
              {
                "seed": 9,
                "name": "TCU",
                "row": 8
              }
            ],
            [
              {
                "seed": 5,
                "name": "St. John's",
                "row": 10
              },
              {
                "seed": 12,
                "name": "Northern Iowa",
                "row": 12
              }
            ],
            [
              {
                "seed": 4,
                "name": "Kansas",
                "row": 14
              },
              {
                "seed": 13,
                "name": "Cal Baptist",
                "row": 16
              }
            ],
            [
              {
                "seed": 6,
                "name": "Louisville",
                "row": 18
              },
              {
                "seed": 11,
                "name": "South Florida",
                "row": 20
              }
            ],
            [
              {
                "seed": 3,
                "name": "Michigan State",
                "row": 22
              },
              {
                "seed": 14,
                "name": "N. Dakota State",
                "row": 24
              }
            ],
            [
              {
                "seed": 7,
                "name": "UCLA",
                "row": 26
              },
              {
                "seed": 10,
                "name": "UCF",
                "row": 28
              }
            ],
            [
              {
                "seed": 2,
                "name": "UConn",
                "row": 30
              },
              {
                "seed": 15,
                "name": "Furman",
                "row": 32
              }
            ]
          ],
          "round_winners": {
            "Round of 32": [
              "Duke",
              "Ohio State",
              "St. John's",
              "Kansas",
              "Louisville",
              "Michigan State",
              "UCLA",
              "UConn"
            ],
            "Sweet 16": [
              "Duke",
              "St. John's",
              "Michigan State",
              "UConn"
            ],
            "Elite 8": [
              "Duke",
              "UConn"
            ],
            "Final Four": [
              "Duke"
            ],
            "Finalist": [
              "Duke"
            ],
            "Champion": [
              "Duke"
            ]
          },
          "name": "South"
        },
        {
          "matchups": [
            [
              {
                "seed": 1,
                "name": "Arizona",
                "row": 2
              },
              {
                "seed": 16,
                "name": "LIU",
                "row": 4
              }
            ],
            [
              {
                "seed": 8,
                "name": "Villanova",
                "row": 6
              },
              {
                "seed": 9,
                "name": "Utah State",
                "row": 8
              }
            ],
            [
              {
                "seed": 5,
                "name": "Wisconsin",
                "row": 10
              },
              {
                "seed": 12,
                "name": "High Point",
                "row": 12
              }
            ],
            [
              {
                "seed": 4,
                "name": "Arkansas",
                "row": 14
              },
              {
                "seed": 13,
                "name": "Hawaii",
                "row": 16
              }
            ],
            [
              {
                "seed": 6,
                "name": "BYU",
                "row": 18
              },
              {
                "seed": 11,
                "name": "TX/NC State",
                "row": 20
              }
            ],
            [
              {
                "seed": 3,
                "name": "Gonzaga",
                "row": 22
              },
              {
                "seed": 14,
                "name": "Kennesaw State",
                "row": 24
              }
            ],
            [
              {
                "seed": 7,
                "name": "Miami (FL)",
                "row": 26
              },
              {
                "seed": 10,
                "name": "Missouri",
                "row": 28
              }
            ],
            [
              {
                "seed": 2,
                "name": "Purdue",
                "row": 30
              },
              {
                "seed": 15,
                "name": "Queens",
                "row": 32
              }
            ]
          ],
          "round_winners": {
            "Round of 32": [
              "Arizona",
              "Utah State",
              "Wisconsin",
              "Arkansas",
              "BYU",
              "Gonzaga",
              "Miami (FL)",
              "Purdue"
            ],
            "Sweet 16": [
              "Arizona",
              "Arkansas",
              "Gonzaga",
              "Purdue"
            ],
            "Elite 8": [
              "Arizona",
              "Purdue"
            ],
            "Final Four": [
              "Arizona"
            ],
            "Finalist": [
              "Arizona"
            ]
          },
          "name": "East"
        },
        {
          "matchups": [
            [
              {
                "seed": 1,
                "name": "Florida",
                "row": 35
              },
              {
                "seed": 16,
                "name": "PV A&M/Lehigh",
                "row": 37
              }
            ],
            [
              {
                "seed": 8,
                "name": "Clemson",
                "row": 39
              },
              {
                "seed": 9,
                "name": "Iowa",
                "row": 41
              }
            ],
            [
              {
                "seed": 5,
                "name": "Vanderbilt",
                "row": 43
              },
              {
                "seed": 12,
                "name": "McNeese",
                "row": 45
              }
            ],
            [
              {
                "seed": 4,
                "name": "Nebraska",
                "row": 47
              },
              {
                "seed": 13,
                "name": "Troy",
                "row": 49
              }
            ],
            [
              {
                "seed": 6,
                "name": "North Carolina",
                "row": 51
              },
              {
                "seed": 11,
                "name": "VCU",
                "row": 53
              }
            ],
            [
              {
                "seed": 3,
                "name": "Illinois",
                "row": 55
              },
              {
                "seed": 14,
                "name": "Penn",
                "row": 57
              }
            ],
            [
              {
                "seed": 7,
                "name": "Saint Mary's",
                "row": 59
              },
              {
                "seed": 10,
                "name": "Texas A&M",
                "row": 61
              }
            ],
            [
              {
                "seed": 2,
                "name": "Houston",
                "row": 63
              },
              {
                "seed": 15,
                "name": "Idaho",
                "row": 65
              }
            ]
          ],
          "round_winners": {
            "Round of 32": [
              "Florida",
              "Iowa",
              "Vanderbilt",
              "Nebraska",
              "North Carolina",
              "Illinois",
              "Saint Mary's",
              "Houston"
            ],
            "Sweet 16": [
              "Florida",
              "Vanderbilt",
              "Illinois",
              "Houston"
            ],
            "Elite 8": [
              "Florida",
              "Houston"
            ],
            "Final Four": [
              "Houston"
            ],
            "Finalist": [],
            "Champion": []
          },
          "name": "West"
        },
        {
          "matchups": [
            [
              {
                "seed": 1,
                "name": "Michigan",
                "row": 35
              },
              {
                "seed": 16,
                "name": "UMBC/Howard",
                "row": 37
              }
            ],
            [
              {
                "seed": 8,
                "name": "Georgia",
                "row": 39
              },
              {
                "seed": 9,
                "name": "Saint Louis",
                "row": 41
              }
            ],
            [
              {
                "seed": 5,
                "name": "Texas Tech",
                "row": 43
              },
              {
                "seed": 12,
                "name": "Akron",
                "row": 45
              }
            ],
            [
              {
                "seed": 4,
                "name": "Alabama",
                "row": 47
              },
              {
                "seed": 13,
                "name": "Hofstra",
                "row": 49
              }
            ],
            [
              {
                "seed": 6,
                "name": "Tennessee",
                "row": 51
              },
              {
                "seed": 11,
                "name": "SMU/Miami OH",
                "row": 53
              }
            ],
            [
              {
                "seed": 3,
                "name": "Virginia",
                "row": 55
              },
              {
                "seed": 14,
                "name": "Wright State",
                "row": 57
              }
            ],
            [
              {
                "seed": 7,
                "name": "Kentucky",
                "row": 59
              },
              {
                "seed": 10,
                "name": "Santa Clara",
                "row": 61
              }
            ],
            [
              {
                "seed": 2,
                "name": "Iowa State",
                "row": 63
              },
              {
                "seed": 15,
                "name": "Tennessee State",
                "row": 65
              }
            ]
          ],
          "round_winners": {
            "Round of 32": [
              "Michigan",
              "Georgia",
              "Texas Tech",
              "Alabama",
              "Tennessee",
              "Virginia",
              "Kentucky",
              "Iowa State"
            ],
            "Sweet 16": [
              "Michigan",
              "Texas Tech",
              "Virginia",
              "Kentucky"
            ],
            "Elite 8": [
              "Michigan",
              "Virginia"
            ],
            "Final Four": [
              "Michigan"
            ],
            "Finalist": []
          },
          "name": "Midwest"
        }
      ]
    },
    {
      "id": "gavin",
      "name": "Gavin",
      "tiebreaker": "82-74",
      "score": 17,
      "regions": [
        {
          "matchups": [
            [
              {
                "seed": 1,
                "name": "Duke",
                "row": 2
              },
              {
                "seed": 16,
                "name": "Siena",
                "row": 4
              }
            ],
            [
              {
                "seed": 8,
                "name": "Ohio State",
                "row": 6
              },
              {
                "seed": 9,
                "name": "TCU",
                "row": 8
              }
            ],
            [
              {
                "seed": 5,
                "name": "St. John's",
                "row": 10
              },
              {
                "seed": 12,
                "name": "Northern Iowa",
                "row": 12
              }
            ],
            [
              {
                "seed": 4,
                "name": "Kansas",
                "row": 14
              },
              {
                "seed": 13,
                "name": "Cal Baptist",
                "row": 16
              }
            ],
            [
              {
                "seed": 6,
                "name": "Louisville",
                "row": 18
              },
              {
                "seed": 11,
                "name": "South Florida",
                "row": 20
              }
            ],
            [
              {
                "seed": 3,
                "name": "Michigan State",
                "row": 22
              },
              {
                "seed": 14,
                "name": "N. Dakota State",
                "row": 24
              }
            ],
            [
              {
                "seed": 7,
                "name": "UCLA",
                "row": 26
              },
              {
                "seed": 10,
                "name": "UCF",
                "row": 28
              }
            ],
            [
              {
                "seed": 2,
                "name": "UConn",
                "row": 30
              },
              {
                "seed": 15,
                "name": "Furman",
                "row": 32
              }
            ]
          ],
          "round_winners": {
            "Round of 32": [
              "Duke",
              "Ohio State",
              "St. John's",
              "Kansas",
              "Louisville",
              "Michigan State",
              "UCLA",
              "UConn"
            ],
            "Sweet 16": [
              "Duke",
              "Kansas",
              "Michigan State",
              "UConn"
            ],
            "Elite 8": [
              "Duke",
              "Michigan State"
            ],
            "Final Four": [
              "Duke"
            ],
            "Finalist": [
              "Duke"
            ],
            "Champion": [
              "Duke"
            ]
          },
          "name": "South"
        },
        {
          "matchups": [
            [
              {
                "seed": 1,
                "name": "Arizona",
                "row": 2
              },
              {
                "seed": 16,
                "name": "LIU",
                "row": 4
              }
            ],
            [
              {
                "seed": 8,
                "name": "Villanova",
                "row": 6
              },
              {
                "seed": 9,
                "name": "Utah State",
                "row": 8
              }
            ],
            [
              {
                "seed": 5,
                "name": "Wisconsin",
                "row": 10
              },
              {
                "seed": 12,
                "name": "High Point",
                "row": 12
              }
            ],
            [
              {
                "seed": 4,
                "name": "Arkansas",
                "row": 14
              },
              {
                "seed": 13,
                "name": "Hawaii",
                "row": 16
              }
            ],
            [
              {
                "seed": 6,
                "name": "BYU",
                "row": 18
              },
              {
                "seed": 11,
                "name": "TX/NC State",
                "row": 20
              }
            ],
            [
              {
                "seed": 3,
                "name": "Gonzaga",
                "row": 22
              },
              {
                "seed": 14,
                "name": "Kennesaw State",
                "row": 24
              }
            ],
            [
              {
                "seed": 7,
                "name": "Miami (FL)",
                "row": 26
              },
              {
                "seed": 10,
                "name": "Missouri",
                "row": 28
              }
            ],
            [
              {
                "seed": 2,
                "name": "Purdue",
                "row": 30
              },
              {
                "seed": 15,
                "name": "Queens",
                "row": 32
              }
            ]
          ],
          "round_winners": {
            "Round of 32": [
              "Arizona",
              "Villanova",
              "Wisconsin",
              "Arkansas",
              "BYU",
              "Gonzaga",
              "Miami (FL)",
              "Purdue"
            ],
            "Sweet 16": [
              "Arizona",
              "Wisconsin",
              "Gonzaga",
              "Purdue"
            ],
            "Elite 8": [
              "Arizona",
              "Purdue"
            ],
            "Final Four": [
              "Purdue"
            ],
            "Finalist": [
              "Purdue"
            ]
          },
          "name": "East"
        },
        {
          "matchups": [
            [
              {
                "seed": 1,
                "name": "Florida",
                "row": 35
              },
              {
                "seed": 16,
                "name": "PV A&M/Lehigh",
                "row": 37
              }
            ],
            [
              {
                "seed": 8,
                "name": "Clemson",
                "row": 39
              },
              {
                "seed": 9,
                "name": "Iowa",
                "row": 41
              }
            ],
            [
              {
                "seed": 5,
                "name": "Vanderbilt",
                "row": 43
              },
              {
                "seed": 12,
                "name": "McNeese",
                "row": 45
              }
            ],
            [
              {
                "seed": 4,
                "name": "Nebraska",
                "row": 47
              },
              {
                "seed": 13,
                "name": "Troy",
                "row": 49
              }
            ],
            [
              {
                "seed": 6,
                "name": "North Carolina",
                "row": 51
              },
              {
                "seed": 11,
                "name": "VCU",
                "row": 53
              }
            ],
            [
              {
                "seed": 3,
                "name": "Illinois",
                "row": 55
              },
              {
                "seed": 14,
                "name": "Penn",
                "row": 57
              }
            ],
            [
              {
                "seed": 7,
                "name": "Saint Mary's",
                "row": 59
              },
              {
                "seed": 10,
                "name": "Texas A&M",
                "row": 61
              }
            ],
            [
              {
                "seed": 2,
                "name": "Houston",
                "row": 63
              },
              {
                "seed": 15,
                "name": "Idaho",
                "row": 65
              }
            ]
          ],
          "round_winners": {
            "Round of 32": [
              "Florida",
              "Iowa",
              "Vanderbilt",
              "Nebraska",
              "North Carolina",
              "Illinois",
              "Saint Mary's",
              "Houston"
            ],
            "Sweet 16": [
              "Florida",
              "Nebraska",
              "North Carolina",
              "Houston"
            ],
            "Elite 8": [
              "Florida",
              "Houston"
            ],
            "Final Four": [
              "Florida"
            ],
            "Finalist": [],
            "Champion": []
          },
          "name": "West"
        },
        {
          "matchups": [
            [
              {
                "seed": 1,
                "name": "Michigan",
                "row": 35
              },
              {
                "seed": 16,
                "name": "UMBC/Howard",
                "row": 37
              }
            ],
            [
              {
                "seed": 8,
                "name": "Georgia",
                "row": 39
              },
              {
                "seed": 9,
                "name": "Saint Louis",
                "row": 41
              }
            ],
            [
              {
                "seed": 5,
                "name": "Texas Tech",
                "row": 43
              },
              {
                "seed": 12,
                "name": "Akron",
                "row": 45
              }
            ],
            [
              {
                "seed": 4,
                "name": "Alabama",
                "row": 47
              },
              {
                "seed": 13,
                "name": "Hofstra",
                "row": 49
              }
            ],
            [
              {
                "seed": 6,
                "name": "Tennessee",
                "row": 51
              },
              {
                "seed": 11,
                "name": "SMU/Miami OH",
                "row": 53
              }
            ],
            [
              {
                "seed": 3,
                "name": "Virginia",
                "row": 55
              },
              {
                "seed": 14,
                "name": "Wright State",
                "row": 57
              }
            ],
            [
              {
                "seed": 7,
                "name": "Kentucky",
                "row": 59
              },
              {
                "seed": 10,
                "name": "Santa Clara",
                "row": 61
              }
            ],
            [
              {
                "seed": 2,
                "name": "Iowa State",
                "row": 63
              },
              {
                "seed": 15,
                "name": "Tennessee State",
                "row": 65
              }
            ]
          ],
          "round_winners": {
            "Round of 32": [
              "Michigan",
              "Saint Louis",
              "Texas Tech",
              "Alabama",
              "Tennessee",
              "Virginia",
              "Kentucky",
              "Iowa State"
            ],
            "Sweet 16": [
              "Michigan",
              "Texas Tech",
              "Virginia",
              "Iowa State"
            ],
            "Elite 8": [
              "Michigan",
              "Virginia"
            ],
            "Final Four": [
              "Michigan"
            ],
            "Finalist": []
          },
          "name": "Midwest"
        }
      ]
    },
    {
      "id": "molly",
      "name": "Molly",
      "tiebreaker": "82-67",
      "score": 15,
      "regions": [
        {
          "matchups": [
            [
              {
                "seed": 1,
                "name": "Duke",
                "row": 2
              },
              {
                "seed": 16,
                "name": "Siena",
                "row": 4
              }
            ],
            [
              {
                "seed": 8,
                "name": "Ohio State",
                "row": 6
              },
              {
                "seed": 9,
                "name": "TCU",
                "row": 8
              }
            ],
            [
              {
                "seed": 5,
                "name": "St. John's",
                "row": 10
              },
              {
                "seed": 12,
                "name": "Northern Iowa",
                "row": 12
              }
            ],
            [
              {
                "seed": 4,
                "name": "Kansas",
                "row": 14
              },
              {
                "seed": 13,
                "name": "Cal Baptist",
                "row": 16
              }
            ],
            [
              {
                "seed": 6,
                "name": "Louisville",
                "row": 18
              },
              {
                "seed": 11,
                "name": "South Florida",
                "row": 20
              }
            ],
            [
              {
                "seed": 3,
                "name": "Michigan State",
                "row": 22
              },
              {
                "seed": 14,
                "name": "N. Dakota State",
                "row": 24
              }
            ],
            [
              {
                "seed": 7,
                "name": "UCLA",
                "row": 26
              },
              {
                "seed": 10,
                "name": "UCF",
                "row": 28
              }
            ],
            [
              {
                "seed": 2,
                "name": "UConn",
                "row": 30
              },
              {
                "seed": 15,
                "name": "Furman",
                "row": 32
              }
            ]
          ],
          "round_winners": {
            "Round of 32": [
              "Duke",
              "Ohio State",
              "St. John's",
              "Kansas",
              "South Florida",
              "Michigan State",
              "UCLA",
              "UConn"
            ],
            "Sweet 16": [
              "Duke",
              "St. John's",
              "Michigan State",
              "UConn"
            ],
            "Elite 8": [
              "Duke",
              "UConn"
            ],
            "Final Four": [
              "Duke"
            ],
            "Finalist": [
              "Duke"
            ],
            "Champion": [
              "Arizona"
            ]
          },
          "name": "South"
        },
        {
          "matchups": [
            [
              {
                "seed": 1,
                "name": "Arizona",
                "row": 2
              },
              {
                "seed": 16,
                "name": "LIU",
                "row": 4
              }
            ],
            [
              {
                "seed": 8,
                "name": "Villanova",
                "row": 6
              },
              {
                "seed": 9,
                "name": "Utah State",
                "row": 8
              }
            ],
            [
              {
                "seed": 5,
                "name": "Wisconsin",
                "row": 10
              },
              {
                "seed": 12,
                "name": "High Point",
                "row": 12
              }
            ],
            [
              {
                "seed": 4,
                "name": "Arkansas",
                "row": 14
              },
              {
                "seed": 13,
                "name": "Hawaii",
                "row": 16
              }
            ],
            [
              {
                "seed": 6,
                "name": "BYU",
                "row": 18
              },
              {
                "seed": 11,
                "name": "TX/NC State",
                "row": 20
              }
            ],
            [
              {
                "seed": 3,
                "name": "Gonzaga",
                "row": 22
              },
              {
                "seed": 14,
                "name": "Kennesaw State",
                "row": 24
              }
            ],
            [
              {
                "seed": 7,
                "name": "Miami (FL)",
                "row": 26
              },
              {
                "seed": 10,
                "name": "Missouri",
                "row": 28
              }
            ],
            [
              {
                "seed": 2,
                "name": "Purdue",
                "row": 30
              },
              {
                "seed": 15,
                "name": "Queens",
                "row": 32
              }
            ]
          ],
          "round_winners": {
            "Round of 32": [
              "Arizona",
              "Utah State",
              "Wisconsin",
              "Arkansas",
              "BYU",
              "Gonzaga",
              "Miami (FL)",
              "Purdue"
            ],
            "Sweet 16": [
              "Arizona",
              "Arkansas",
              "Gonzaga",
              "Purdue"
            ],
            "Elite 8": [
              "Arizona",
              "Purdue"
            ],
            "Final Four": [
              "Arizona"
            ],
            "Finalist": [
              "Arizona"
            ]
          },
          "name": "East"
        },
        {
          "matchups": [
            [
              {
                "seed": 1,
                "name": "Florida",
                "row": 35
              },
              {
                "seed": 16,
                "name": "PV A&M/Lehigh",
                "row": 37
              }
            ],
            [
              {
                "seed": 8,
                "name": "Clemson",
                "row": 39
              },
              {
                "seed": 9,
                "name": "Iowa",
                "row": 41
              }
            ],
            [
              {
                "seed": 5,
                "name": "Vanderbilt",
                "row": 43
              },
              {
                "seed": 12,
                "name": "McNeese",
                "row": 45
              }
            ],
            [
              {
                "seed": 4,
                "name": "Nebraska",
                "row": 47
              },
              {
                "seed": 13,
                "name": "Troy",
                "row": 49
              }
            ],
            [
              {
                "seed": 6,
                "name": "North Carolina",
                "row": 51
              },
              {
                "seed": 11,
                "name": "VCU",
                "row": 53
              }
            ],
            [
              {
                "seed": 3,
                "name": "Illinois",
                "row": 55
              },
              {
                "seed": 14,
                "name": "Penn",
                "row": 57
              }
            ],
            [
              {
                "seed": 7,
                "name": "Saint Mary's",
                "row": 59
              },
              {
                "seed": 10,
                "name": "Texas A&M",
                "row": 61
              }
            ],
            [
              {
                "seed": 2,
                "name": "Houston",
                "row": 63
              },
              {
                "seed": 15,
                "name": "Idaho",
                "row": 65
              }
            ]
          ],
          "round_winners": {
            "Round of 32": [
              "Florida",
              "Iowa",
              "Vanderbilt",
              "Nebraska",
              "North Carolina",
              "Illinois",
              "Saint Mary's",
              "Houston"
            ],
            "Sweet 16": [
              "Florida",
              "Vanderbilt",
              "Illinois",
              "Houston"
            ],
            "Elite 8": [
              "Florida",
              "Houston"
            ],
            "Final Four": [
              "Florida"
            ],
            "Finalist": [],
            "Champion": []
          },
          "name": "West"
        },
        {
          "matchups": [
            [
              {
                "seed": 1,
                "name": "Michigan",
                "row": 35
              },
              {
                "seed": 16,
                "name": "UMBC/Howard",
                "row": 37
              }
            ],
            [
              {
                "seed": 8,
                "name": "Georgia",
                "row": 39
              },
              {
                "seed": 9,
                "name": "Saint Louis",
                "row": 41
              }
            ],
            [
              {
                "seed": 5,
                "name": "Texas Tech",
                "row": 43
              },
              {
                "seed": 12,
                "name": "Akron",
                "row": 45
              }
            ],
            [
              {
                "seed": 4,
                "name": "Alabama",
                "row": 47
              },
              {
                "seed": 13,
                "name": "Hofstra",
                "row": 49
              }
            ],
            [
              {
                "seed": 6,
                "name": "Tennessee",
                "row": 51
              },
              {
                "seed": 11,
                "name": "SMU/Miami OH",
                "row": 53
              }
            ],
            [
              {
                "seed": 3,
                "name": "Virginia",
                "row": 55
              },
              {
                "seed": 14,
                "name": "Wright State",
                "row": 57
              }
            ],
            [
              {
                "seed": 7,
                "name": "Kentucky",
                "row": 59
              },
              {
                "seed": 10,
                "name": "Santa Clara",
                "row": 61
              }
            ],
            [
              {
                "seed": 2,
                "name": "Iowa State",
                "row": 63
              },
              {
                "seed": 15,
                "name": "Tennessee State",
                "row": 65
              }
            ]
          ],
          "round_winners": {
            "Round of 32": [
              "Michigan",
              "Georgia",
              "Texas Tech",
              "Alabama",
              "Tennessee",
              "Virginia",
              "Kentucky",
              "Iowa State"
            ],
            "Sweet 16": [
              "Michigan",
              "Alabama",
              "Virginia",
              "Kentucky"
            ],
            "Elite 8": [
              "Michigan",
              "Virginia"
            ],
            "Final Four": [
              "Michigan"
            ],
            "Finalist": []
          },
          "name": "Midwest"
        }
      ]
    }
  ]
}